README.md
setup.py
gcpi/__init__.py
gcpi/stackdriverlog/__init__.py
gcpi/stackdriverlog/conf.py
gcpi/stackdriverlog/formatters.py
gcpi/stackdriverlog/loggers.py
gcpi/stackdriverlog/settings.py
gcpi/stackdriverlog/contrib/__init__.py
gcpi/stackdriverlog/contrib/compat.py
gcpi/stackdriverlog/contrib/django/__init__.py
gcpi/stackdriverlog/contrib/django/apps.py
gcpi/stackdriverlog/contrib/django/middleware.py
gcpi/stackdriverlog/contrib/flask/__init__.py
python_gcp_injections.egg-info/PKG-INFO
python_gcp_injections.egg-info/SOURCES.txt
python_gcp_injections.egg-info/dependency_links.txt
python_gcp_injections.egg-info/requires.txt
python_gcp_injections.egg-info/top_level.txt