Metadata-Version: 2.1
Name: python-gcp-injections
Version: 1.5.1
Summary: Tools and libraries for python to better run services on GCP
Home-page: https://github.com/injectedreality/python-gcp-injections
Author: Tommy Strand
Author-email: github-projects@ireality.no
License: UNKNOWN
Keywords: stackdriver django gcp logging gke
Platform: UNKNOWN
Classifier: Programming Language :: Python :: 3
Classifier: License :: OSI Approved :: MIT License
Classifier: Operating System :: OS Independent
Requires-Python: >=3.6
